[
  {
    "id" : "f6bb40e6-d66f-4831-8c8e-57d001e96687",
    "prId" : 22162,
    "prUrl" : "https://github.com/DefinitelyTyped/DefinitelyTyped/pull/22162#pullrequestreview-85414671",
    "prSource" : "GitHub",
    "comments" : [
      {
        "id" : "d683b3f3-f965-413c-8fc1-fd9bead99c84",
        "parentId" : null,
        "authorId" : "12d669e7-71ea-4328-9d11-c67c19345ed6",
        "body" : "Why 2 newlines? Consider removing the second.",
        "createdAt" : "2017-12-23T02:14:00Z",
        "updatedAt" : "2017-12-23T02:14:00Z",
        "lastEditedBy" : "12d669e7-71ea-4328-9d11-c67c19345ed6",
        "tags" : [
        ]
      }
    ],
    "commit" : "c07a61d1aa2f0cc628df15f09853dfe1872868c4",
    "line" : 35,
    "diffHunk" : "@@ -1,1 +1392,1396 @@      datepicker(methodName: 'option', optionName: 'autohide'): boolean;\n\n\n      /**\n      * Get the endDate after initialization"
  }
]