[
  {
    "id" : "2e42cad3-dcdf-45df-b4e9-78e72846257f",
    "prId" : 110,
    "prUrl" : "https://github.com/akka/alpakka/pull/110#pullrequestreview-32801574",
    "prSource" : "GitHub",
    "comments" : [
      {
        "id" : "10c3f9cc-36c4-4967-beb3-2bff73c4c830",
        "parentId" : null,
        "authorId" : "8173970f-6a3f-4891-8394-179e8251af2d",
        "body" : "It would be great to have a simple test written in Java that would validate if the Java Dsl is alright.",
        "createdAt" : "2017-04-14T08:55:55Z",
        "updatedAt" : "2017-04-14T12:48:15Z",
        "lastEditedBy" : "8173970f-6a3f-4891-8394-179e8251af2d",
        "tags" : [
        ]
      }
    ],
    "commit" : "ce9239e45d61a17c2fe8087035cddd6858967f2e",
    "line" : 23,
    "diffHunk" : "@@ -1,1 +21,25 @@trait CommittableMessage extends Committable {\n  def message: Message\n}"
  }
]