[
  {
    "id" : "7f8c92a4-3966-4c97-8e86-8b0da65a752a",
    "prId" : 5893,
    "prUrl" : "https://github.com/apache/kafka/pull/5893#pullrequestreview-198748713",
    "prSource" : "GitHub",
    "comments" : [
      {
        "id" : "a99fe002-1b55-4ec8-a885-f1dc3424ce56",
        "parentId" : null,
        "authorId" : "442b5138-0781-4001-8ac5-0593f2136d1c",
        "body" : "This comment is for Timestamp, not for Offset?",
        "createdAt" : "2019-01-25T23:40:45Z",
        "updatedAt" : "2019-01-25T23:41:25Z",
        "lastEditedBy" : "442b5138-0781-4001-8ac5-0593f2136d1c",
        "tags" : [
        ]
      },
      {
        "id" : "a957da6d-685b-42b9-9853-7b8623f5fc48",
        "parentId" : "a99fe002-1b55-4ec8-a885-f1dc3424ce56",
        "authorId" : "514c0afb-8649-4fd9-a6ea-ee9e1b695274",
        "body" : "Good catch.  I have filed a PR to fix this: https://github.com/apache/kafka/pull/6214",
        "createdAt" : "2019-01-31T18:35:59Z",
        "updatedAt" : "2019-01-31T18:35:59Z",
        "lastEditedBy" : "514c0afb-8649-4fd9-a6ea-ee9e1b695274",
        "tags" : [
        ]
      }
    ],
    "commit" : "6d8de7a5c2839b05e6d3143f9ef0e31832234abf",
    "line" : 44,
    "diffHunk" : "@@ -1,1 +42,46 @@        { \"name\": \"Timestamp\", \"type\": \"int64\", \"versions\": \"1+\" },\n        { \"name\": \"Offset\", \"type\": \"int64\", \"versions\": \"1+\",\n          \"about\": \"The timestamp associated with the returned offset.\" },\n        { \"name\": \"LeaderEpoch\", \"type\": \"int32\", \"versions\": \"4+\" }\n      ]}"
  },
  {
    "id" : "864eab68-1377-4c0b-af4c-bf48d96b0928",
    "prId" : 8295,
    "prUrl" : "https://github.com/apache/kafka/pull/8295#pullrequestreview-491442896",
    "prSource" : "GitHub",
    "comments" : [
      {
        "id" : "4802f6c9-709e-4804-a51b-f68e6dc9c73c",
        "parentId" : null,
        "authorId" : "3dfe0270-df82-43af-827f-0681ce1c6ad9",
        "body" : "Why do we need this default?",
        "createdAt" : "2020-09-17T19:27:36Z",
        "updatedAt" : "2020-09-24T09:26:37Z",
        "lastEditedBy" : "3dfe0270-df82-43af-827f-0681ce1c6ad9",
        "tags" : [
        ]
      },
      {
        "id" : "0d9d5661-eb05-4834-b17b-376e316b17d1",
        "parentId" : "4802f6c9-709e-4804-a51b-f68e6dc9c73c",
        "authorId" : "d31db46e-de6d-4fea-8dc5-6f7b17b636be",
        "body" : "Until now, this field is an Optional and it's defaulted to `-1` in https://github.com/apache/kafka/blob/trunk/clients/src/main/java/org/apache/kafka/common/requests/RequestUtils.java#L30-L32\r\n\r\nOtherwise an `int32` default value is `0` with the generator code",
        "createdAt" : "2020-09-18T13:02:15Z",
        "updatedAt" : "2020-09-24T09:26:37Z",
        "lastEditedBy" : "d31db46e-de6d-4fea-8dc5-6f7b17b636be",
        "tags" : [
        ]
      }
    ],
    "commit" : "78cb96fc13e5c337372b24b5ea50d7ade30485fc",
    "line" : 5,
    "diffHunk" : "@@ -1,1 +49,53 @@        { \"name\": \"Offset\", \"type\": \"int64\", \"versions\": \"1+\", \"default\": \"-1\", \"ignorable\": false,\n          \"about\": \"The returned offset.\" },\n        { \"name\": \"LeaderEpoch\", \"type\": \"int32\", \"versions\": \"4+\", \"default\": \"-1\" }\n      ]}\n    ]}"
  }
]