[
  {
    "id" : "599c02fa-6ac8-487b-83c4-3ad31d9b58d3",
    "prId" : 446,
    "prUrl" : null,
    "prSource" : "GitHub",
    "comments" : [
      {
        "id" : "4daa595d-3960-4106-bb18-d0dc5b934e08",
        "parentId" : null,
        "authorId" : "a3f1fdb0-47ad-411e-b63d-af6fc71a1fa6",
        "body" : "Probably can cut this extra whitespace.\n",
        "createdAt" : "2016-04-21T19:03:30Z",
        "updatedAt" : "2016-05-09T23:10:27Z",
        "lastEditedBy" : "a3f1fdb0-47ad-411e-b63d-af6fc71a1fa6",
        "tags" : [
        ]
      }
    ],
    "commit" : "6abc431b4474b900f8310ce7d8620f5ea86baeee",
    "line" : null,
    "diffHunk" : "@@ -1,1 +23,27 @@  export LDFLAGS=\"${LDFLAGS} -L${PREFIX}/lib\"\nfi\n\n./configure --prefix=${PREFIX} --with-python=\"${PYTHON}\" --with-libiconv=gnu \\\n  || { cat config.log; exit 1; }"
  },
  {
    "id" : "c7d00d76-6feb-430c-aeff-af817d4111fd",
    "prId" : 446,
    "prUrl" : null,
    "prSource" : "GitHub",
    "comments" : [
      {
        "id" : "6e8f4592-3623-4c9e-a064-5e46e7ff1c58",
        "parentId" : null,
        "authorId" : "a3f1fdb0-47ad-411e-b63d-af6fc71a1fa6",
        "body" : "Though honestly this doesn't look so bad to me.\n",
        "createdAt" : "2016-05-09T20:27:34Z",
        "updatedAt" : "2016-05-09T23:10:27Z",
        "lastEditedBy" : "a3f1fdb0-47ad-411e-b63d-af6fc71a1fa6",
        "tags" : [
        ]
      },
      {
        "id" : "0e18b06c-3c80-4741-9e27-87ba20b33a1a",
        "parentId" : "6e8f4592-3623-4c9e-a064-5e46e7ff1c58",
        "authorId" : "4a3ee9f8-9e7c-459e-b715-28669578f2c0",
        "body" : "Yeah.  I could try removing the `--with-python` perhaps\n",
        "createdAt" : "2016-05-09T20:28:42Z",
        "updatedAt" : "2016-05-09T23:10:27Z",
        "lastEditedBy" : "4a3ee9f8-9e7c-459e-b715-28669578f2c0",
        "tags" : [
        ]
      },
      {
        "id" : "ea5c02a0-2f6c-4dd0-8092-130f05f7aaf5",
        "parentId" : "6e8f4592-3623-4c9e-a064-5e46e7ff1c58",
        "authorId" : "a3f1fdb0-47ad-411e-b63d-af6fc71a1fa6",
        "body" : "Is the `--with-libiconv` support to have a path? Should we be using `--with-pcre` too? Not sure if there are any more `--with-*` we should fill in.\n",
        "createdAt" : "2016-05-09T23:20:50Z",
        "updatedAt" : "2016-05-09T23:20:50Z",
        "lastEditedBy" : "a3f1fdb0-47ad-411e-b63d-af6fc71a1fa6",
        "tags" : [
        ]
      },
      {
        "id" : "8133194e-20b6-4107-b228-3f5fab989966",
        "parentId" : "6e8f4592-3623-4c9e-a064-5e46e7ff1c58",
        "authorId" : "4a3ee9f8-9e7c-459e-b715-28669578f2c0",
        "body" : "`--with-libiconv` is needed so it compiles.  Not sure about `--with-pcre`, though it is a dependency.  Maybe we can worry about this in the feedstock too?\n",
        "createdAt" : "2016-05-09T23:23:12Z",
        "updatedAt" : "2016-05-09T23:23:12Z",
        "lastEditedBy" : "4a3ee9f8-9e7c-459e-b715-28669578f2c0",
        "tags" : [
        ]
      }
    ],
    "commit" : "6abc431b4474b900f8310ce7d8620f5ea86baeee",
    "line" : 26,
    "diffHunk" : "@@ -1,1 +24,28 @@fi\n\n./configure --prefix=${PREFIX} --with-python=\"${PYTHON}\" --with-libiconv=gnu \\\n  || { cat config.log; exit 1; }\nmake"
  },
  {
    "id" : "7c241fb1-216b-45db-865e-c9ae6a780ae2",
    "prId" : 446,
    "prUrl" : null,
    "prSource" : "GitHub",
    "comments" : [
      {
        "id" : "3adfa564-5ff5-4a07-90c6-5139703881f8",
        "parentId" : null,
        "authorId" : "a3f1fdb0-47ad-411e-b63d-af6fc71a1fa6",
        "body" : "I don't think I have ever seen this. What is this doing?\n",
        "createdAt" : "2016-05-09T20:28:37Z",
        "updatedAt" : "2016-05-09T23:10:27Z",
        "lastEditedBy" : "a3f1fdb0-47ad-411e-b63d-af6fc71a1fa6",
        "tags" : [
        ]
      },
      {
        "id" : "ed2945d6-8cc1-48e1-9ca1-14f742518fcb",
        "parentId" : "3adfa564-5ff5-4a07-90c6-5139703881f8",
        "authorId" : "4a3ee9f8-9e7c-459e-b715-28669578f2c0",
        "body" : "This is a custom thing for one of the patches. I just copied this directly, though I could probably pretty easily change it to another variable name if you'd like.\n",
        "createdAt" : "2016-05-09T20:30:40Z",
        "updatedAt" : "2016-05-09T23:10:27Z",
        "lastEditedBy" : "4a3ee9f8-9e7c-459e-b715-28669578f2c0",
        "tags" : [
        ]
      }
    ],
    "commit" : "6abc431b4474b900f8310ce7d8620f5ea86baeee",
    "line" : null,
    "diffHunk" : "@@ -1,1 +3,7 @@# Need to get appropriate response to g_get_system_data_dirs()\n# See the system-data-dirs.patch file\nexport CFLAGS=\"-DCONDA_SYSTEM_DATA_DIRS=\\\\\\\"${PREFIX}/share\\\\\\\"\"\n\nif [ \"$(uname)\" == \"Darwin\" ] ; then"
  },
  {
    "id" : "f3389211-fbe8-4531-a79e-dc3e5c537c50",
    "prId" : 446,
    "prUrl" : null,
    "prSource" : "GitHub",
    "comments" : [
      {
        "id" : "9a5128b0-4c89-4d63-ae3d-4cd251fdb7ff",
        "parentId" : null,
        "authorId" : "a3f1fdb0-47ad-411e-b63d-af6fc71a1fa6",
        "body" : "Are we brave enough to try `make check`? I forget whether they provided the option or not.\n",
        "createdAt" : "2016-05-09T21:04:40Z",
        "updatedAt" : "2016-05-09T23:10:27Z",
        "lastEditedBy" : "a3f1fdb0-47ad-411e-b63d-af6fc71a1fa6",
        "tags" : [
        ]
      },
      {
        "id" : "772d8d97-0b6f-41fe-b919-be7df58ba8db",
        "parentId" : "9a5128b0-4c89-4d63-ae3d-4cd251fdb7ff",
        "authorId" : "4a3ee9f8-9e7c-459e-b715-28669578f2c0",
        "body" : "Fortune favors **the**. I'll try it after the current experiment.\n",
        "createdAt" : "2016-05-09T21:10:33Z",
        "updatedAt" : "2016-05-09T23:10:27Z",
        "lastEditedBy" : "4a3ee9f8-9e7c-459e-b715-28669578f2c0",
        "tags" : [
        ]
      },
      {
        "id" : "8317884b-07ed-42d1-ab5a-ff47cdd46db8",
        "parentId" : "9a5128b0-4c89-4d63-ae3d-4cd251fdb7ff",
        "authorId" : "4a3ee9f8-9e7c-459e-b715-28669578f2c0",
        "body" : "There is an extraneous error that causes the check to fail. Can't find any info about it, so it is probably a bug\n\n```\nPASS: fileutils 1 /fileutils/build-path\nPASS: fileutils 2 /fileutils/build-pathv\nPASS: fileutils 3 /fileutils/build-filename\nPASS: fileutils 4 /fileutils/build-filenamev\nPASS: fileutils 5 /fileutils/mkdir-with-parents\nPASS: fileutils 6 /fileutils/format-size-for-display\nPASS: fileutils 7 /fileutils/errors\nPASS: fileutils 8 /fileutils/basename\nPASS: fileutils 9 /fileutils/dir-make-tmp\nPASS: fileutils 10 /fileutils/file-open-tmp\nPASS: fileutils 11 /fileutils/mkstemp\nPASS: fileutils 12 /fileutils/mkdtemp\nPASS: fileutils 13 /fileutils/set-contents\nPASS: fileutils 14 /fileutils/read-link\nERROR: fileutils - too few tests run (expected 15, got 14)\nERROR: fileutils - exited with status 134 (terminated by signal 6?)\n```\n",
        "createdAt" : "2016-05-09T22:33:09Z",
        "updatedAt" : "2016-05-09T23:10:27Z",
        "lastEditedBy" : "4a3ee9f8-9e7c-459e-b715-28669578f2c0",
        "tags" : [
        ]
      },
      {
        "id" : "3e7fba29-a225-46d8-adf3-b507431093d3",
        "parentId" : "9a5128b0-4c89-4d63-ae3d-4cd251fdb7ff",
        "authorId" : "a3f1fdb0-47ad-411e-b63d-af6fc71a1fa6",
        "body" : "Was just looking at that. Not finding lots of info ATM.\n",
        "createdAt" : "2016-05-09T22:33:56Z",
        "updatedAt" : "2016-05-09T23:10:27Z",
        "lastEditedBy" : "a3f1fdb0-47ad-411e-b63d-af6fc71a1fa6",
        "tags" : [
        ]
      },
      {
        "id" : "7803a0d2-a950-449a-b036-3bc194880427",
        "parentId" : "9a5128b0-4c89-4d63-ae3d-4cd251fdb7ff",
        "authorId" : "a3f1fdb0-47ad-411e-b63d-af6fc71a1fa6",
        "body" : "Looks like the issue is we are missing `desktop-file-utils` according [LFS](http://www.linuxfromscratch.org/blfs/view/svn/general/glib2.html). It appears to have a cyclic dependency with `glib`. So, we might have to do the same thing we did with `bison` and `flex`, which is build one (with tests disabled) and then build the other. Finally, we enable the tests after both are built.\n",
        "createdAt" : "2016-05-09T22:38:42Z",
        "updatedAt" : "2016-05-09T23:10:27Z",
        "lastEditedBy" : "a3f1fdb0-47ad-411e-b63d-af6fc71a1fa6",
        "tags" : [
        ]
      },
      {
        "id" : "83275aa8-5167-4f68-a76c-500d86e018c6",
        "parentId" : "9a5128b0-4c89-4d63-ae3d-4cd251fdb7ff",
        "authorId" : "4a3ee9f8-9e7c-459e-b715-28669578f2c0",
        "body" : "I see, that seems reasonable.\n",
        "createdAt" : "2016-05-09T22:39:40Z",
        "updatedAt" : "2016-05-09T23:10:27Z",
        "lastEditedBy" : "4a3ee9f8-9e7c-459e-b715-28669578f2c0",
        "tags" : [
        ]
      }
    ],
    "commit" : "6abc431b4474b900f8310ce7d8620f5ea86baeee",
    "line" : 28,
    "diffHunk" : "@@ -1,1 +26,30 @@./configure --prefix=${PREFIX} --with-python=\"${PYTHON}\" --with-libiconv=gnu \\\n  || { cat config.log; exit 1; }\nmake\nmake install"
  },
  {
    "id" : "a408847f-6947-4cbc-bc49-a8412c279ebc",
    "prId" : 446,
    "prUrl" : null,
    "prSource" : "GitHub",
    "comments" : [
      {
        "id" : "5d86881f-41ea-4a46-aa85-2e1b0f5d36c3",
        "parentId" : null,
        "authorId" : "a3f1fdb0-47ad-411e-b63d-af6fc71a1fa6",
        "body" : "I see now. This is being used with `system-data-dirs.patch`. Maybe we should reference that patch here. Sorry for being confused.\n",
        "createdAt" : "2016-05-09T22:48:51Z",
        "updatedAt" : "2016-05-09T23:10:27Z",
        "lastEditedBy" : "a3f1fdb0-47ad-411e-b63d-af6fc71a1fa6",
        "tags" : [
        ]
      },
      {
        "id" : "b528b531-9322-4bbe-97f0-f3c6035f95c4",
        "parentId" : "5d86881f-41ea-4a46-aa85-2e1b0f5d36c3",
        "authorId" : "4a3ee9f8-9e7c-459e-b715-28669578f2c0",
        "body" : "done.\n",
        "createdAt" : "2016-05-09T22:51:18Z",
        "updatedAt" : "2016-05-09T23:10:27Z",
        "lastEditedBy" : "4a3ee9f8-9e7c-459e-b715-28669578f2c0",
        "tags" : [
        ]
      }
    ],
    "commit" : "6abc431b4474b900f8310ce7d8620f5ea86baeee",
    "line" : null,
    "diffHunk" : "@@ -1,1 +3,7 @@# Need to get appropriate response to g_get_system_data_dirs()\n# See the system-data-dirs.patch file\nexport CFLAGS=\"-DCONDA_SYSTEM_DATA_DIRS=\\\\\\\"${PREFIX}/share\\\\\\\"\"\n\nif [ \"$(uname)\" == \"Darwin\" ] ; then"
  }
]