[
  {
    "id" : "a71ed681-ff01-4ba2-ae79-d9e427154f4a",
    "prId" : 21309,
    "prUrl" : "https://github.com/RocketChat/Rocket.Chat/pull/21309#pullrequestreview-625432310",
    "prSource" : "GitHub",
    "comments" : [
      {
        "id" : "83efdd08-44c6-4037-a8b6-c0597eb60853",
        "parentId" : null,
        "authorId" : "e286e399-a847-4b77-8052-d1ba61e04074",
        "body" : "```suggestion\r\n\t\t\t... priorityId && { priorityId },\r\n\t\t};\r\n```",
        "createdAt" : "2021-03-31T15:31:53Z",
        "updatedAt" : "2021-03-31T18:03:57Z",
        "lastEditedBy" : "e286e399-a847-4b77-8052-d1ba61e04074",
        "tags" : [
        ]
      }
    ],
    "commit" : "7882cdcea30408f15209d406bdf00a139dd8507c",
    "line" : 171,
    "diffHunk" : "@@ -1,1 +184,188 @@\t\t\tlivechatData,\n\t\t\t...priorityId && { priorityId },\n\t\t};\n\n\t\ttry {"
  }
]