[
  {
    "id" : "273dfed8-478c-4cf6-bd10-2726012bd01b",
    "prId" : 34599,
    "prUrl" : "https://github.com/flutter/flutter/pull/34599#pullrequestreview-263859255",
    "prSource" : "GitHub",
    "comments" : [
      {
        "id" : "a68d6ce7-260c-49c9-a240-37b2f4bdd794",
        "parentId" : null,
        "authorId" : "9ae618fc-fa71-4bc9-be97-de7c674590eb",
        "body" : "It would be good to reiterate a version of this ToggleButtonsTheme point here:\r\n```\r\n/// Values specified here are used for [ToggleButtons] properties that are not\r\n/// given an explicit non-null value.\r\n```\r\n",
        "createdAt" : "2019-07-18T19:22:38Z",
        "updatedAt" : "2019-07-25T18:13:05Z",
        "lastEditedBy" : "9ae618fc-fa71-4bc9-be97-de7c674590eb",
        "tags" : [
        ]
      }
    ],
    "commit" : "6a4c0b960231cc25c69046d80e6e1daea77ef85a",
    "line" : 19,
    "diffHunk" : "@@ -1,1 +17,21 @@///\n/// To obtain the current [ToggleButtonsTheme], use [ToggleButtonsTheme.of].\n///\n/// Values specified here are used for [ToggleButtons] properties that are not\n/// given an explicit non-null value."
  },
  {
    "id" : "b940f249-bf18-4259-aeab-b1a94aa48274",
    "prId" : 34599,
    "prUrl" : "https://github.com/flutter/flutter/pull/34599#pullrequestreview-263859255",
    "prSource" : "GitHub",
    "comments" : [
      {
        "id" : "e6aaad2a-ea9d-40e6-abde-87311bb1a4a9",
        "parentId" : null,
        "authorId" : "9ae618fc-fa71-4bc9-be97-de7c674590eb",
        "body" : "Should explain that if the there's no enclosing ToggleButtonsTheme widget, then Theme.of(context).toggleButtonsTheme is used (and it's unlikely to be null).",
        "createdAt" : "2019-07-18T22:08:36Z",
        "updatedAt" : "2019-07-25T18:13:05Z",
        "lastEditedBy" : "9ae618fc-fa71-4bc9-be97-de7c674590eb",
        "tags" : [
        ]
      }
    ],
    "commit" : "6a4c0b960231cc25c69046d80e6e1daea77ef85a",
    "line" : 255,
    "diffHunk" : "@@ -1,1 +253,257 @@  final ToggleButtonsThemeData data;\n\n  /// The closest instance of this class that encloses the given context.\n  ///\n  /// If there is no enclosing [ToggleButtonsTheme] widget, then"
  }
]