[
  {
    "id" : "b9f1ce5c-8e44-4f64-b256-532b9950f023",
    "prId" : 10411,
    "prUrl" : null,
    "prSource" : "GitHub",
    "comments" : [
      {
        "id" : "e823ba84-fc14-4784-b2f4-0eb8c478d252",
        "parentId" : null,
        "authorId" : "c9b2af00-2c8d-4a67-9cb5-7cbedac7e233",
        "body" : "Unrelated fix, I think ?\n",
        "createdAt" : "2015-03-08T00:49:27Z",
        "updatedAt" : "2015-03-10T22:40:24Z",
        "lastEditedBy" : "c9b2af00-2c8d-4a67-9cb5-7cbedac7e233",
        "tags" : [
        ]
      },
      {
        "id" : "e46bd05c-e3d9-4d07-9637-2d946981b6e3",
        "parentId" : "e823ba84-fc14-4784-b2f4-0eb8c478d252",
        "authorId" : "30fc1801-f8f1-4cc4-9690-e31e203f4f6d",
        "body" : "yes, I think i snuck in a couple.\n",
        "createdAt" : "2015-03-08T01:09:55Z",
        "updatedAt" : "2015-03-10T22:40:24Z",
        "lastEditedBy" : "30fc1801-f8f1-4cc4-9690-e31e203f4f6d",
        "tags" : [
        ]
      }
    ],
    "commit" : "5f6db0e16477749c1bccf472150132ca06c50b3b",
    "line" : 96,
    "diffHunk" : "@@ -1,1 +180,184 @@        # calling utils.boolean(None) returns False\n        self.gather_facts = ds.get('gather_facts', None)\n        if self.gather_facts is not None:\n            self.gather_facts = utils.boolean(self.gather_facts)\n"
  },
  {
    "id" : "564175b0-4075-45d5-a7a8-0d327f657c9e",
    "prId" : 10411,
    "prUrl" : null,
    "prSource" : "GitHub",
    "comments" : [
      {
        "id" : "553ed3b8-399a-4b42-b5fe-15252562a841",
        "parentId" : null,
        "authorId" : null,
        "body" : "Ansible Play? You mean Playbook?\n",
        "createdAt" : "2015-03-09T20:26:19Z",
        "updatedAt" : "2015-03-10T22:40:24Z",
        "lastEditedBy" : null,
        "tags" : [
        ]
      },
      {
        "id" : "18eb7ae6-805f-4fed-9603-32f5ecbf8454",
        "parentId" : "553ed3b8-399a-4b42-b5fe-15252562a841",
        "authorId" : "30fc1801-f8f1-4cc4-9690-e31e203f4f6d",
        "body" : "No, its Play, a playbook itself has no keys or anything else than plays, plays have keys and paramters.\n",
        "createdAt" : "2015-03-09T20:28:06Z",
        "updatedAt" : "2015-03-10T22:40:24Z",
        "lastEditedBy" : "30fc1801-f8f1-4cc4-9690-e31e203f4f6d",
        "tags" : [
        ]
      },
      {
        "id" : "58a6c4dd-dfc4-4b2b-8752-37b60a6e5fbf",
        "parentId" : "553ed3b8-399a-4b42-b5fe-15252562a841",
        "authorId" : null,
        "body" : "My mistake; didn't fully understand the context and previous line referenced \"Playbook\". Thanks for the clarification.\n",
        "createdAt" : "2015-03-09T20:31:46Z",
        "updatedAt" : "2015-03-10T22:40:24Z",
        "lastEditedBy" : null,
        "tags" : [
        ]
      },
      {
        "id" : "481d23fa-f99a-4093-97b1-c0e98e195dbf",
        "parentId" : "553ed3b8-399a-4b42-b5fe-15252562a841",
        "authorId" : "30fc1801-f8f1-4cc4-9690-e31e203f4f6d",
        "body" : "it is an unrelated change, but i opportunistically sneaked  the correction in.\n",
        "createdAt" : "2015-03-09T20:33:25Z",
        "updatedAt" : "2015-03-10T22:40:24Z",
        "lastEditedBy" : "30fc1801-f8f1-4cc4-9690-e31e203f4f6d",
        "tags" : [
        ]
      }
    ],
    "commit" : "5f6db0e16477749c1bccf472150132ca06c50b3b",
    "line" : 45,
    "diffHunk" : "@@ -1,1 +60,64 @@        for x in ds.keys():\n            if not x in Play.VALID_KEYS:\n                raise errors.AnsibleError(\"%s is not a legal parameter of an Ansible Play\" % x)\n\n        # allow all playbook keys to be set by --extra-vars"
  },
  {
    "id" : "d1c7fb4e-0ead-4ee1-b9ce-e2005f26466c",
    "prId" : 56354,
    "prUrl" : "https://github.com/ansible/ansible/pull/56354#pullrequestreview-236867939",
    "prSource" : "GitHub",
    "comments" : [
      {
        "id" : "d9d9c5bf-ee8d-46ab-b45b-09d2fb458741",
        "parentId" : null,
        "authorId" : "30fc1801-f8f1-4cc4-9690-e31e203f4f6d",
        "body" : "this is not a correct fix, it fails  for ```hosts: [ None, host1, host2]```",
        "createdAt" : "2019-05-13T19:17:37Z",
        "updatedAt" : "2019-05-14T15:48:44Z",
        "lastEditedBy" : "30fc1801-f8f1-4cc4-9690-e31e203f4f6d",
        "tags" : [
        ]
      }
    ],
    "commit" : "b8d109413509c7e10188d34c61b6083c862b9993",
    "line" : 5,
    "diffHunk" : "@@ -1,1 +105,109 @@        if ('name' not in data or data['name'] is None) and 'hosts' in data:\n            if data['hosts'] is None or all(host is None for host in data['hosts']):\n                raise AnsibleParserError(\"Hosts list cannot be empty - please check your playbook\")\n            if isinstance(data['hosts'], list):\n                data['name'] = ','.join(data['hosts'])"
  },
  {
    "id" : "10a5cb44-e841-4d47-b282-346754de3e38",
    "prId" : 74147,
    "prUrl" : "https://github.com/ansible/ansible/pull/74147#pullrequestreview-686606241",
    "prSource" : "GitHub",
    "comments" : [
      {
        "id" : "628d00f3-ab0e-43a3-91d3-ef1519816a3c",
        "parentId" : null,
        "authorId" : "30fc1801-f8f1-4cc4-9690-e31e203f4f6d",
        "body" : "remove 116 and 117 as dupes",
        "createdAt" : "2021-06-17T17:23:25Z",
        "updatedAt" : "2021-06-17T17:23:29Z",
        "lastEditedBy" : "30fc1801-f8f1-4cc4-9690-e31e203f4f6d",
        "tags" : [
        ]
      }
    ],
    "commit" : "3c87b13617370725d8bce66c323b7acf32db47ca",
    "line" : 27,
    "diffHunk" : "@@ -1,1 +112,116 @@                    elif not isinstance(entry, (binary_type, text_type)):\n                        raise AnsibleParserError(\"Hosts list contains an invalid host value: '{host!s}'\".format(host=entry))\n\n            elif not isinstance(value, (binary_type, text_type)):\n                raise AnsibleParserError(\"Hosts list must be a sequence or string. Please check your playbook.\")"
  }
]