[
  {
    "id" : "24d1d1f7-af80-4b6d-8b7e-f37e3aefb702",
    "prId" : 696,
    "prUrl" : null,
    "prSource" : "GitHub",
    "comments" : [
      {
        "id" : "382e0e23-ee6d-4650-a4ee-36ed6c6213b2",
        "parentId" : null,
        "authorId" : "d1d1486d-a9d6-4052-8ee5-6141a9338ca4",
        "body" : "Why `TAPi18next.t('project:Username_invalid', username)`?\nThe translation should not be done on the server side, as the client may be using a different language.\n",
        "createdAt" : "2015-09-06T02:39:03Z",
        "updatedAt" : "2015-09-06T02:39:03Z",
        "lastEditedBy" : "d1d1486d-a9d6-4052-8ee5-6141a9338ca4",
        "tags" : [
        ]
      },
      {
        "id" : "b2ee2b56-dcc2-461b-a676-e9285f3880a9",
        "parentId" : "382e0e23-ee6d-4650-a4ee-36ed6c6213b2",
        "authorId" : "2bbfae4c-b224-415d-996b-ab094d48faa6",
        "body" : "Still new to Meteor, unsure which pieces fit where. I assumed the client data got passed down and translated then passed back up to the server.\n\nSorry!  I'll read the docs better next time.\n",
        "createdAt" : "2015-09-06T02:43:54Z",
        "updatedAt" : "2015-09-06T02:43:54Z",
        "lastEditedBy" : "2bbfae4c-b224-415d-996b-ab094d48faa6",
        "tags" : [
        ]
      }
    ],
    "commit" : "78fb56939909df453f0e7998492c6a8c6eb4f9ed",
    "line" : 5,
    "diffHunk" : "@@ -1,1 +12,16 @@\n\t\tif not /^[0-9a-zA-Z-_.]+$/.test username\n\t\t\tthrow new Meteor.Error 'username-invalid', TAPi18next.t('project:Username_invalid', username)\n\n\t\tif not RocketChat.checkUsernameAvailability username"
  }
]