[
  {
    "id" : "4ec98058-02e7-4948-a9a1-e479c4688d8a",
    "prId" : 1960,
    "prUrl" : "https://github.com/conda-forge/staged-recipes/pull/1960#pullrequestreview-9230884",
    "prSource" : "GitHub",
    "comments" : [
      {
        "id" : "1bed5e74-8aab-4542-8347-5a68cae0dbb4",
        "parentId" : null,
        "authorId" : "085a9c6b-569e-49bd-9434-7f128372cf0c",
        "body" : "Add to the build section the necessary entry points:\n\n```\nbuild:\n...\n  entry_points:\n    - nestrun = nestly.scripts.nestrun:main\n    - nestagg = nestly.scripts.nestagg:main\n```\n",
        "createdAt" : "2016-11-18T14:21:06Z",
        "updatedAt" : "2016-11-18T20:27:23Z",
        "lastEditedBy" : "085a9c6b-569e-49bd-9434-7f128372cf0c",
        "tags" : [
        ]
      }
    ],
    "commit" : "10dcecce97951713993bc733f4b8d164e4a6cb1e",
    "line" : null,
    "diffHunk" : "@@ -1,1 +24,28 @@    - setuptools\n  run:\n    - python\n\ntest:"
  },
  {
    "id" : "557581fa-103a-4c4a-b3e8-55029922eb0a",
    "prId" : 1960,
    "prUrl" : "https://github.com/conda-forge/staged-recipes/pull/1960#pullrequestreview-9230884",
    "prSource" : "GitHub",
    "comments" : [
      {
        "id" : "daa7da06-dc30-4240-9ade-17be799297d4",
        "parentId" : null,
        "authorId" : "085a9c6b-569e-49bd-9434-7f128372cf0c",
        "body" : "Add command tests:\n\n```\ntest:\n  ...\n  commands:\n    - nestrun --help\n    - nestagg --help \n```\n",
        "createdAt" : "2016-11-18T14:22:14Z",
        "updatedAt" : "2016-11-18T20:27:23Z",
        "lastEditedBy" : "085a9c6b-569e-49bd-9434-7f128372cf0c",
        "tags" : [
        ]
      }
    ],
    "commit" : "10dcecce97951713993bc733f4b8d164e4a6cb1e",
    "line" : null,
    "diffHunk" : "@@ -1,1 +28,32 @@test:\n  imports:\n    - nestly\n  commands:\n    - nestrun --help"
  }
]