[
  {
    "id" : "807c5e4e-a328-44aa-ad5d-45ffa168e223",
    "prId" : 2221,
    "prUrl" : "https://github.com/typelevel/cats/pull/2221#pullrequestreview-109919283",
    "prSource" : "GitHub",
    "comments" : [
      {
        "id" : "237eca01-66f0-4d08-b4d6-7592230bb024",
        "parentId" : null,
        "authorId" : "6b760ef7-e448-44a7-b744-0c25c840a80a",
        "body" : "I guess we can write here: \r\nOne of the best ways to provide examples is doctest, here is an [example of doctest examples in cats](https://github.com/typelevel/cats/blob/master/core/src/main/scala/cats/Functor.scala#L19-L33). ",
        "createdAt" : "2018-04-06T00:36:32Z",
        "updatedAt" : "2018-04-09T15:40:49Z",
        "lastEditedBy" : "6b760ef7-e448-44a7-b744-0c25c840a80a",
        "tags" : [
        ]
      }
    ],
    "commit" : "1f1e7825ee995a07a94c2c17ae62a7e16ffb0b24",
    "line" : 85,
    "diffHunk" : "@@ -1,1 +209,213 @@staying up-to-date.\n\n### Write examples\n\nOne of the best ways to provide examples is doctest, here is [an example](https://github.com/typelevel/cats/blob/master/core/src/main/scala/cats/Functor.scala#L19-L33). Doctest is a [sbt plugin](https://github.com/tkawachi/sbt-doctest) which generates tests based on the syntax mentioned above and runs when sbt's `test` task is invoked. You can find more information in the plugin documentation."
  }
]