[
  {
    "id" : "6412cb91-ca75-4739-9101-16fdeaf100c1",
    "prId" : 7738,
    "prUrl" : null,
    "prSource" : "GitHub",
    "comments" : [
      {
        "id" : "2cc28e46-52cf-469f-b12e-7473d2979966",
        "parentId" : null,
        "authorId" : "7086d5c0-382b-4c41-b70d-144a07643f71",
        "body" : "say fixes the issue where...... and non-unique columns (instead of multiple columsn with the same name)\n",
        "createdAt" : "2014-07-24T18:22:02Z",
        "updatedAt" : "2014-07-24T23:10:13Z",
        "lastEditedBy" : "7086d5c0-382b-4c41-b70d-144a07643f71",
        "tags" : [
        ]
      },
      {
        "id" : "c3e96554-fc12-4c70-9330-8954f0b155ed",
        "parentId" : "2cc28e46-52cf-469f-b12e-7473d2979966",
        "authorId" : "8b404822-a597-42dd-b567-818788cb72c8",
        "body" : "Updated. Better now?\n",
        "createdAt" : "2014-07-24T18:27:10Z",
        "updatedAt" : "2014-07-24T23:10:13Z",
        "lastEditedBy" : "8b404822-a597-42dd-b567-818788cb72c8",
        "tags" : [
        ]
      }
    ],
    "commit" : "34d2910f0f789fface33b43c0bb6b6e3ec7ae903",
    "line" : 14,
    "diffHunk" : "@@ -1,1 +279,283 @@- Bug in ``StataReader`` which did not read variable labels in 117 files due to difference between Stata documentation and implementation (:issue:`7816`)\n\n- Bug in ``expanding_cov``, ``expanding_corr``, ``rolling_cov``, ``rolling_cov``, ``ewmcov``, and ``ewmcorr``\n  returning results with columns sorted by name and producing an error for non-unique columns;\n  now handles non-unique columns and returns columns in original order"
  },
  {
    "id" : "de60f23a-791b-48dd-ae51-33ff046153f8",
    "prId" : 7738,
    "prUrl" : null,
    "prSource" : "GitHub",
    "comments" : [
      {
        "id" : "18541797-4656-402c-bdd5-fda6598b2d16",
        "parentId" : null,
        "authorId" : "7086d5c0-382b-4c41-b70d-144a07643f71",
        "body" : "put the issue you are closing here instead of the PR issue\n",
        "createdAt" : "2014-07-24T19:30:47Z",
        "updatedAt" : "2014-07-24T23:10:13Z",
        "lastEditedBy" : "7086d5c0-382b-4c41-b70d-144a07643f71",
        "tags" : [
        ]
      },
      {
        "id" : "ebe07dd6-d7b7-4fda-aa3f-7c9e827f78be",
        "parentId" : "18541797-4656-402c-bdd5-fda6598b2d16",
        "authorId" : "8b404822-a597-42dd-b567-818788cb72c8",
        "body" : "Oops. Just noticed this. Will change reference from 7738 to 7542. (Though the line you commented on was simply me deleting an extra space from someone else's bug.)\n",
        "createdAt" : "2014-07-24T23:08:16Z",
        "updatedAt" : "2014-07-24T23:10:13Z",
        "lastEditedBy" : "8b404822-a597-42dd-b567-818788cb72c8",
        "tags" : [
        ]
      },
      {
        "id" : "c7bd16a6-1d8e-4c9d-aeed-eca8ebab883a",
        "parentId" : "18541797-4656-402c-bdd5-fda6598b2d16",
        "authorId" : "7086d5c0-382b-4c41-b70d-144a07643f71",
        "body" : "ah ok....thanks for the fix\n",
        "createdAt" : "2014-07-24T23:11:56Z",
        "updatedAt" : "2014-07-24T23:11:56Z",
        "lastEditedBy" : "7086d5c0-382b-4c41-b70d-144a07643f71",
        "tags" : [
        ]
      }
    ],
    "commit" : "34d2910f0f789fface33b43c0bb6b6e3ec7ae903",
    "line" : 5,
    "diffHunk" : "@@ -1,1 +266,270 @@\n\n- Bug in repeated timeseries line and area plot may result in ``ValueError`` or incorrect kind (:issue:`7733`)\n\n"
  }
]