[
  {
    "id" : "4fa735b5-7601-4631-bdb8-dcc011fab17f",
    "prId" : 67060,
    "prUrl" : "https://github.com/kubernetes/kubernetes/pull/67060#pullrequestreview-145305600",
    "prSource" : "GitHub",
    "comments" : [
      {
        "id" : "7716726e-92d4-4cdc-b7cb-3bbde8a64f7a",
        "parentId" : null,
        "authorId" : "bfe6ebf1-cfa7-4758-abb1-9960fa09b194",
        "body" : "Can we get rid of these in v1.13?",
        "createdAt" : "2018-08-10T16:14:10Z",
        "updatedAt" : "2018-08-17T06:57:30Z",
        "lastEditedBy" : "bfe6ebf1-cfa7-4758-abb1-9960fa09b194",
        "tags" : [
        ]
      }
    ],
    "commit" : "c2724793e8ff47fc5961762a874ac74b9169bed1",
    "line" : 88,
    "diffHunk" : "@@ -1,1 +86,90 @@\n\tfs.IPVar(&s.BindAddress, \"address\", s.BindAddress,\n\t\t\"DEPRECATED: see --bind-address instead.\")\n\tfs.MarkDeprecated(\"address\", \"see --bind-address instead.\")\n"
  }
]