[
  {
    "id" : "a93eead7-75ef-47b2-b01c-615873d89461",
    "prId" : 49271,
    "prUrl" : "https://github.com/ansible/ansible/pull/49271#pullrequestreview-200845680",
    "prSource" : "GitHub",
    "comments" : [
      {
        "id" : "d7ec1935-1a68-4787-8eed-1470249f9e23",
        "parentId" : null,
        "authorId" : "7268595c-1eb4-4b5f-9277-90f183130a4b",
        "body" : "```suggestion\r\n        - Create or modify an organization.\r\n      type: str\r\n```\r\nPlease add types for all parameters !",
        "createdAt" : "2019-02-06T22:47:09Z",
        "updatedAt" : "2019-03-01T01:47:19Z",
        "lastEditedBy" : "7268595c-1eb4-4b5f-9277-90f183130a4b",
        "tags" : [
        ]
      }
    ],
    "commit" : "e5f265396e0c62d617239f85762acf2f3a983a1f",
    "line" : 32,
    "diffHunk" : "@@ -1,1 +30,34 @@    state:\n        description:\n        - Create or modify an organization.\n        choices: [ absent, query, present ]\n        default: present"
  }
]