[
  {
    "id" : "f9bd33b5-4bea-4fb9-baca-27c374aee413",
    "prId" : 3818,
    "prUrl" : null,
    "prSource" : "GitHub",
    "comments" : [
      {
        "id" : "6e0b9325-d9ae-48c1-9759-fbb29766355f",
        "parentId" : null,
        "authorId" : "aeb7e171-52e2-4faa-8a7c-32d6a9d2c2be",
        "body" : "Think maybe this should say \"unit of the arg (s,ms,us,ns) if passed an epoch\", will do that in that pr\n",
        "createdAt" : "2013-06-13T19:12:15Z",
        "updatedAt" : "2013-06-13T19:12:15Z",
        "lastEditedBy" : "aeb7e171-52e2-4faa-8a7c-32d6a9d2c2be",
        "tags" : [
        ]
      },
      {
        "id" : "ca55d81c-1c60-4ade-93a8-d9590c15ca2f",
        "parentId" : "6e0b9325-d9ae-48c1-9759-fbb29766355f",
        "authorId" : "7086d5c0-382b-4c41-b70d-144a07643f71",
        "body" : "go ahed....just merged\n",
        "createdAt" : "2013-06-13T19:16:13Z",
        "updatedAt" : "2013-06-13T19:16:13Z",
        "lastEditedBy" : "7086d5c0-382b-4c41-b70d-144a07643f71",
        "tags" : [
        ]
      }
    ],
    "commit" : "fbcd5abcadb37c612804aefc5255e2e99b009444",
    "line" : 13,
    "diffHunk" : "@@ -1,1 +70,74 @@        strftime to parse time, eg \"%d/%m/%Y\"\n    coerce : force errors to NaT (False by default)\n    unit : unit of the arg (s,ms,us,ns) denote the unit in epoch\n        (e.g. a unix timestamp), which is an integer/float number\n"
  }
]