[
  {
    "id" : "039d11b5-4a02-4661-b7e3-1ceaf098df62",
    "prId" : 2002,
    "prUrl" : "https://github.com/akka/alpakka/pull/2002#pullrequestreview-317278939",
    "prSource" : "GitHub",
    "comments" : [
      {
        "id" : "dc3a8d5f-1f38-4c98-bd5d-81acde4924b9",
        "parentId" : null,
        "authorId" : "daac5cb5-ce57-4037-a06c-7adf6a3f10e6",
        "body" : "@ennru Oops, I just spotted this.  I assume these should have read:\r\n\r\n> *closed in 2.0.0-M1*.",
        "createdAt" : "2019-11-14T21:41:48Z",
        "updatedAt" : "2019-11-14T21:41:48Z",
        "lastEditedBy" : "daac5cb5-ce57-4037-a06c-7adf6a3f10e6",
        "tags" : [
        ]
      }
    ],
    "commit" : "e3f56f0a3c57f694c1b04f91ba14814c1d213f9b",
    "line" : 7,
    "diffHunk" : "@@ -1,1 +5,9 @@No changes.\n\n[*closed in 2.2.0-M1*](https://github.com/akka/alpakka/issues?q=is%3Aclosed+milestone%3A2.0.0-M1+label%3Ap%3Aamqp)\n\nFor earlier changes see @ref:[1.1.x versions](../1.1.x/amqp.md)"
  }
]