[
  {
    "id" : "31ac8387-11da-4fbb-9dbf-1c2502466fb3",
    "prId" : 6481,
    "prUrl" : "https://github.com/apache/kafka/pull/6481#pullrequestreview-230301931",
    "prSource" : "GitHub",
    "comments" : [
      {
        "id" : "f8504a46-4b79-49c5-8e52-c176bf8389c0",
        "parentId" : null,
        "authorId" : "5c21df64-97d8-46ab-9722-a7e9ba1d7c49",
        "body" : "Should we do the same thing for `--help`?",
        "createdAt" : "2019-04-23T21:01:47Z",
        "updatedAt" : "2019-04-24T19:11:44Z",
        "lastEditedBy" : "5c21df64-97d8-46ab-9722-a7e9ba1d7c49",
        "tags" : [
        ]
      },
      {
        "id" : "89097a9b-7d69-490c-be6b-155dce8a862f",
        "parentId" : "f8504a46-4b79-49c5-8e52-c176bf8389c0",
        "authorId" : "2f3fbc93-2875-4df0-8f43-329c41f891e4",
        "body" : "I've added an _or_ed option along the lines of what other classes do.\r\nShould I extract that change into a different PR, it is not strictly speaking \"in scope\" for this one..",
        "createdAt" : "2019-04-24T19:07:59Z",
        "updatedAt" : "2019-04-24T19:31:57Z",
        "lastEditedBy" : "2f3fbc93-2875-4df0-8f43-329c41f891e4",
        "tags" : [
        ]
      }
    ],
    "commit" : "049be2c27d9832140a1ff0c81460a8632d2eddb9",
    "line" : 15,
    "diffHunk" : "@@ -1,1 +45,49 @@    }\n\n    if (args.contains(\"--version\")) {\n      CommandLineUtils.printVersionAndDie()\n    }"
  },
  {
    "id" : "51ce1b0e-92b8-4aaa-8e62-7c3d2bafb5d7",
    "prId" : 9934,
    "prUrl" : "https://github.com/apache/kafka/pull/9934#pullrequestreview-573676096",
    "prSource" : "GitHub",
    "comments" : [
      {
        "id" : "12e2febe-e9bd-4b07-ba83-b71dc12a0107",
        "parentId" : null,
        "authorId" : "3dfe0270-df82-43af-827f-0681ce1c6ad9",
        "body" : "What if we call `processRoles.isDefined` here?",
        "createdAt" : "2021-01-21T17:34:16Z",
        "updatedAt" : "2021-01-21T19:45:26Z",
        "lastEditedBy" : "3dfe0270-df82-43af-827f-0681ce1c6ad9",
        "tags" : [
        ]
      },
      {
        "id" : "bbcb4d47-6810-4c64-a4e3-3f6b1a52a801",
        "parentId" : "12e2febe-e9bd-4b07-ba83-b71dc12a0107",
        "authorId" : "5c21df64-97d8-46ab-9722-a7e9ba1d7c49",
        "body" : "Hmm `requiresZookeeper` seemed more explicit. I thought using `processRoles` was a little obscure.",
        "createdAt" : "2021-01-21T19:42:15Z",
        "updatedAt" : "2021-01-21T19:45:26Z",
        "lastEditedBy" : "5c21df64-97d8-46ab-9722-a7e9ba1d7c49",
        "tags" : [
        ]
      }
    ],
    "commit" : "50fa8e955b3f146b624224917374eaf06575a71b",
    "line" : 5,
    "diffHunk" : "@@ -1,1 +66,70 @@  private def buildServer(props: Properties): Server = {\n    val config = KafkaConfig.fromProps(props, false)\n    if (config.requiresZookeeper) {\n      new KafkaServer(\n        config,"
  }
]