[
  {
    "id" : "553e93cb-d3c2-469b-8758-c16934e12001",
    "prId" : 14338,
    "prUrl" : "https://github.com/conda-forge/staged-recipes/pull/14338#pullrequestreview-617377347",
    "prSource" : "GitHub",
    "comments" : [
      {
        "id" : "c28bf687-d9cd-4d8f-97ba-85314faedc10",
        "parentId" : null,
        "authorId" : "c299267b-13d3-4165-bdd2-383eea98be0c",
        "body" : "```suggestion\r\n    - {{ name }}\r\n  commands:\r\n    - pip check\r\n  requires:\r\n    - pip\r\n```",
        "createdAt" : "2021-03-22T10:45:29Z",
        "updatedAt" : "2021-03-22T12:02:06Z",
        "lastEditedBy" : "c299267b-13d3-4165-bdd2-383eea98be0c",
        "tags" : [
        ]
      }
    ],
    "commit" : "fd061a62f65393cd45df6869baf5be70d225046f",
    "line" : 33,
    "diffHunk" : "@@ -1,1 +31,35 @@test:\n  imports:\n    - {{ name }}\n  commands:\n    - pip check"
  },
  {
    "id" : "2879d1f6-a64d-42ca-8cd1-c647e9d246f2",
    "prId" : 14338,
    "prUrl" : "https://github.com/conda-forge/staged-recipes/pull/14338#pullrequestreview-617377347",
    "prSource" : "GitHub",
    "comments" : [
      {
        "id" : "8554b769-db27-458d-8a26-5cc7c4c67963",
        "parentId" : null,
        "authorId" : "d838053f-6fcd-47a0-a593-accf1cf846b0",
        "body" : "```suggestion\r\n    - {{ name }}\r\n  commands:\r\n    - pip check\r\n  requires:\r\n    - pip\r\n```",
        "createdAt" : "2021-03-22T10:45:29Z",
        "updatedAt" : "2021-03-22T12:02:06Z",
        "lastEditedBy" : "d838053f-6fcd-47a0-a593-accf1cf846b0",
        "tags" : [
        ]
      }
    ],
    "commit" : "fd061a62f65393cd45df6869baf5be70d225046f",
    "line" : 33,
    "diffHunk" : "@@ -1,1 +31,35 @@test:\n  imports:\n    - {{ name }}\n  commands:\n    - pip check"
  }
]