[
  {
    "id" : "06b5f911-ef19-447d-aa33-46d6922f21e8",
    "prId" : 65044,
    "prUrl" : "https://github.com/ansible/ansible/pull/65044#pullrequestreview-334737577",
    "prSource" : "GitHub",
    "comments" : [
      {
        "id" : "66837be3-81e3-412d-b3a0-9c6cb157e297",
        "parentId" : null,
        "authorId" : "d10c46ef-3d4c-4766-bd09-d27ec4674a84",
        "body" : "```suggestion\r\n- terraform - fixes usage for providers not supporting workspaces (https://github.com/ansible/ansible/issues/64788).\r\n```",
        "createdAt" : "2019-12-19T16:06:55Z",
        "updatedAt" : "2019-12-19T16:08:03Z",
        "lastEditedBy" : "d10c46ef-3d4c-4766-bd09-d27ec4674a84",
        "tags" : [
        ]
      }
    ],
    "commit" : "7f09c256854cee7d6fa3d7e80523b1e81bf76297",
    "line" : 2,
    "diffHunk" : "@@ -1,1 +0,4 @@bugfixes:\n- terraform module - fixes usage for providers not supporting workspaces"
  }
]